Metadata-Version: 2.1
Name: sythe.py
Version: 1.0.1
Summary: A script that interacts with the Sythe website using Chrome drivers
Home-page: https://github.com/AlexFlipnote/Sythe.py
Author: AlexFlipnote
License: UNKNOWN
Platform: UNKNOWN
